{
  "content": [
    {
      "content": null,
      "created": "2025-04-26T01:00:09.412449Z",
      "format": null,
      "hash": null,
      "hash_algorithm": null,
      "last_modified": "2025-04-26T00:59:34.338689Z",
      "mimetype": null,
      "name": "calc_dbm_watts_conversion.ipynb",
      "path": "calc_dbm_watts_conversion/calc_dbm_watts_conversion.ipynb",
      "size": 89143,
      "type": "notebook",
      "writable": true
    },
    {
      "content": null,
      "created": "2025-04-26T01:00:09.413449Z",
      "format": null,
      "hash": null,
      "hash_algorithm": null,
      "last_modified": "2025-04-26T00:59:34.338689Z",
      "mimetype": "text/x-python",
      "name": "calc_dbm_watts_conversion.py",
      "path": "calc_dbm_watts_conversion/calc_dbm_watts_conversion.py",
      "size": 1872,
      "type": "file",
      "writable": true
    }
  ],
  "created": "2025-04-26T01:00:09.412449Z",
  "format": "json",
  "hash": null,
  "hash_algorithm": null,
  "last_modified": "2025-04-26T01:00:09.412449Z",
  "mimetype": null,
  "name": "calc_dbm_watts_conversion",
  "path": "calc_dbm_watts_conversion",
  "size": null,
  "type": "directory",
  "writable": true
}