{
  "content": [
    {
      "content": null,
      "created": "2025-04-25T16:37:12.180046Z",
      "format": null,
      "hash": null,
      "hash_algorithm": null,
      "last_modified": "2025-04-25T16:36:37.708024Z",
      "mimetype": null,
      "name": "calc_smd_capacitor.ipynb",
      "path": "calc_smd_capacitor/calc_smd_capacitor.ipynb",
      "size": 62,
      "type": "notebook",
      "writable": true
    }
  ],
  "created": "2025-04-25T16:37:12.180046Z",
  "format": "json",
  "hash": null,
  "hash_algorithm": null,
  "last_modified": "2025-04-25T16:37:12.180046Z",
  "mimetype": null,
  "name": "calc_smd_capacitor",
  "path": "calc_smd_capacitor",
  "size": null,
  "type": "directory",
  "writable": true
}